pypelinez/__init__.py
pypelinez/apple.py
pypelinez/click_ext.py
pypelinez/feature.py
pypelinez/git.py
pypelinez/main.py
pypelinez/publish.py
pypelinez/python.py
pypelinez/release.py
pypelinez/utilities.py
pypelinez-0.6.10.dist-info/entry_points.txt
pypelinez-0.6.10.dist-info/LICENSE.md
pypelinez-0.6.10.dist-info/WHEEL
pypelinez-0.6.10.dist-info/METADATA
pypelinez-0.6.10.dist-info/RECORD
